{
	"name": "해남 청무화과 친환경 무농약 생과 재래종 바나네 (1.4kg 20과-26과)",
	"vendor": "싱싱모아팜.",
	"picUrl": "https://shopping-phinf.pstatic.net/main_8342787/83427876237.jpg",
	"thumbnailUrl": "https://shop-phinf.pstatic.net/20210924_68/1632461229496Qp6eK_JPEG/33597072184853287_553134784.jpg?type=f100",
	"price": "22900",
	"deliveryFee": "0",
	"detailpicUrl": [
		"https://img-shop.pstatic.net/front/common/certification/mark_5.gif?type=f65_65",
		"https://shop-phinf.pstatic.net/20220831_88/1661917489295QvQtt_GIF/%EC%A0%84%EC%B2%B4%EA%B3%B5%EC%A7%80_%EB%A6%AC%EB%B7%B0.gif?type=wg860",
		"https://shop-phinf.pstatic.net/20220913_150/1663039313194Camos_PNG/%ED%92%88%EC%A7%88%EB%B3%B4%EC%A6%9D%EC%A0%84%EC%B2%B4%EA%B3%B5%EC%A7%80%ED%86%A1%ED%86%A1_.png?type=w860",
		"https://video-phinf.pstatic.net/20210925_293/1632541750536u99U1_JPEG/88e9397a-1db3-11ec-a613-505dac8c38f5_03.jpg?type=s100",
		"https://video-phinf.pstatic.net/20210925_92/1632541750666VSqXc_JPEG/88e9397a-1db3-11ec-a613-505dac8c38f5_06.jpg?type=s100",
		"https://video-phinf.pstatic.net/20210925_51/16325417507685aYQS_JPEG/88e9397a-1db3-11ec-a613-505dac8c38f5_09.jpg?type=s100",
		"https://shop-phinf.pstatic.net/20210925_183/1632541910515skKtn_GIF/%ED%95%B4%EB%82%A8_%ED%96%87%EB%AC%B4%ED%99%94%EA%B3%BC_%EC%B2%AD%EB%AC%B4%ED%99%94%EA%B3%BC_%EB%95%85%EB%81%9D%EB%AC%B4%ED%99%94%EA%B3%BC_(6).gif?type=wg860",
		"https://shop-phinf.pstatic.net/20210925_188/1632542043114M6IWP_JPEG/SE-04853c3a-53ba-40f8-a7e4-8f06b4ee4821.jpg?type=w860",
		"https://shop-phinf.pstatic.net/20210925_264/1632542056092zHsC8_GIF/%ED%95%B4%EB%82%A8%EB%AC%B4%ED%99%94%EA%B3%BC_%EC%B2%AD%EB%AC%B4%ED%99%94%EA%B3%BC_%EB%AC%B4%EB%86%8D%EC%95%BD%EB%AC%B4%ED%99%94%EA%B3%BC_%EC%83%9D%EB%AC%B4%ED%99%94%EA%B3%BC.gif?type=wg860",
		"https://shop-phinf.pstatic.net/20210925_178/1632542073147diSy5_GIF/%ED%95%B4%EB%82%A8_%ED%96%87%EB%AC%B4%ED%99%94%EA%B3%BC_%EC%B2%AD%EB%AC%B4%ED%99%94%EA%B3%BC_%EB%95%85%EB%81%9D%EB%AC%B4%ED%99%94%EA%B3%BC_(4).gif?type=wg860",
		"https://shop-phinf.pstatic.net/20210925_22/1632542386837nueDV_JPEG/%EB%AC%B4%ED%99%94%EA%B3%BC%EB%A8%B9%EB%8A%94%EB%B2%95-%EC%83%9D%ED%81%AC%EB%A6%BC_%ED%96%87%EB%AC%B4%ED%99%94%EA%B3%BC.jpg?type=w860",
		"https://shop-phinf.pstatic.net/20210925_274/1632542420380B3olq_JPEG/%EA%B1%B4%EB%AC%B4%ED%99%94%EA%B3%BC_%EC%9E%AC%EB%9E%98%EC%A2%85.jpg?type=w860",
		"https://shop-phinf.pstatic.net/20210925_145/1632542440543eYHyz_JPEG/%EB%B0%94%EB%82%98%EB%84%A4-%EC%B2%AD%EB%AC%B4%ED%99%94%EA%B3%BC_%ED%96%87%EB%AC%B4%ED%99%94%EA%B3%BC.jpg?type=w860",
		"https://shop-phinf.pstatic.net/20210925_40/1632542517308xQezd_JPEG/%EC%B2%AD%EB%AC%B4%ED%99%94%EA%B3%BC-%ED%95%B4%EB%82%A8%EB%AC%B4%ED%99%94%EA%B3%BC-2%ED%8C%A9_%EB%AC%B4%EB%86%8D%EC%95%BD.jpg?type=w860",
		"https://shop-phinf.pstatic.net/20210925_57/1632542532784oi6nx_JPEG/%EC%B2%AD%EB%AC%B4%ED%99%94%EA%B3%BC-%ED%95%B4%EB%82%A8%EB%AC%B4%ED%99%94%EA%B3%BC-4%ED%8C%A9_%EB%AC%B4%EB%86%8D%EC%95%BD.jpg?type=w860",
		"https://shop-phinf.pstatic.net/20210925_194/1632542560696yzrvE_GIF/%ED%95%B4%EB%82%A8_%ED%96%87%EB%AC%B4%ED%99%94%EA%B3%BC_%EC%B2%AD%EB%AC%B4%ED%99%94%EA%B3%BC_%EB%95%85%EB%81%9D%EB%AC%B4%ED%99%94%EA%B3%BC_(5).gif?type=wg860",
		"https://shop-phinf.pstatic.net/20210925_78/1632542741431zIeA7_JPEG/%EC%B2%AD%EB%AC%B4%ED%99%94%EA%B3%BC%EC%9E%AC%EB%9E%98%EC%A2%85%EB%AC%B4%ED%99%94%EA%B3%BC_%EB%B0%94%EB%82%98%EB%84%A4.jpg?type=w860",
		"https://shop-phinf.pstatic.net/20210925_246/1632542702751DUwUb_JPEG/KakaoTalk_20200730_225726034.jpg?type=w860",
		"https://shop-phinf.pstatic.net/20210925_40/1632542763947mulJz_JPEG/%EC%83%9D%EB%AC%B4%ED%99%94%EA%B3%BC-%EA%B1%B4%EB%AC%B4%ED%99%94%EA%B3%BC_%EB%AC%B4%EB%86%8D%EC%95%BD.jpg?type=w860",
		"https://shop-phinf.pstatic.net/20210925_43/16325427885859J0H9_JPEG/%EB%95%85%EB%81%9D%EB%AC%B4%ED%99%94%EA%B3%BC_%ED%95%B4%EB%82%A8%EB%AC%B4%ED%99%94%EA%B3%BC.jpg?type=w860",
		"https://shop-phinf.pstatic.net/20210925_66/1632542812776nDcfm_JPEG/%ED%95%B4%EB%82%A8%EC%B2%AD%EB%AC%B4%ED%99%94%EA%B3%BC-%EC%82%AC%EC%9D%B4%EC%A6%88_%EC%A0%84%EB%82%A8%EB%AC%B4%ED%99%94%EA%B3%BC.jpg?type=w860",
		"https://shop-phinf.pstatic.net/20210925_30/1632542829681GTC5R_GIF/%ED%95%B4%EB%82%A8_%ED%96%87%EB%AC%B4%ED%99%94%EA%B3%BC_%EC%B2%AD%EB%AC%B4%ED%99%94%EA%B3%BC_%EB%95%85%EB%81%9D%EB%AC%B4%ED%99%94%EA%B3%BC_(3).gif?type=wg860",
		"https://shop-phinf.pstatic.net/20210925_127/16325428658079Eb19_JPEG/%EC%9E%AC%EB%9E%98%EC%A2%85-%EB%AC%B4%ED%99%94%EA%B3%BC_%ED%95%B4%EB%82%A8%EB%AC%B4%ED%99%94%EA%B3%BC.jpg?type=w860",
		"https://shop-phinf.pstatic.net/20210925_198/1632542880973wN1Wu_JPEG/%ED%95%B4%EB%82%A8-%EC%B2%AD%EB%AC%B4%ED%99%94%EA%B3%BC-%EB%86%8D%EC%9E%A5_%ED%96%87%EB%AC%B4%ED%99%94%EA%B3%BC.jpg?type=w860",
		"https://shop-phinf.pstatic.net/20210925_266/1632542916699R81O1_GIF/%ED%95%B4%EB%82%A8_%ED%96%87%EB%AC%B4%ED%99%94%EA%B3%BC_%EC%B2%AD%EB%AC%B4%ED%99%94%EA%B3%BC_%EB%95%85%EB%81%9D%EB%AC%B4%ED%99%94%EA%B3%BC_(3).gif?type=wg860",
		"https://shop-phinf.pstatic.net/20200816_246/1597541270434OVCa3_JPEG/%EC%98%81%EC%95%94_%EB%AC%B4%ED%99%94%EA%B3%BC_(1).jpg?type=w860",
		"https://shop-phinf.pstatic.net/20200816_52/1597541270871absjC_JPEG/%EC%98%81%EC%95%94_%EB%AC%B4%ED%99%94%EA%B3%BC_(11).jpg?type=w860",
		"https://shop-phinf.pstatic.net/20210925_205/1632542944207AxygS_JPEG/%EC%B2%AD%EB%AC%B4%ED%99%94%EA%B3%BC-%EC%9E%AC%EB%9E%98%EC%A2%85_%EB%B0%94%EB%82%98%EB%84%A4.jpg?type=w860",
		"https://shop-phinf.pstatic.net/20210924_173/1632473116389GzoWG_JPEG/%ED%95%B4%EB%82%A8%EC%B2%AD%EB%AC%B4%ED%99%94%EA%B3%BC-%EA%B0%9C%EB%B3%84%ED%8F%AC%EC%9E%A5.jpg?type=w860",
		"https://shop-phinf.pstatic.net/20210925_262/1632543002962CTqd1_JPEG/%EC%B2%AD%EB%AC%B4%ED%99%94%EA%B3%BC_%EA%B0%9C%EB%B3%84%ED%8F%AC%EC%9E%A5.jpg?type=w860",
		"https://shop-phinf.pstatic.net/20210925_77/1632543014471aDrMW_JPEG/%ED%95%B4%EB%82%A8%EB%AC%B4%ED%99%94%EA%B3%BC-%EC%B2%AD%EB%AC%B4%ED%99%94%EA%B3%BC-%EC%95%84%EC%9D%B4%EC%8A%A4%EB%B0%95%EC%8A%A4%ED%8F%AC%EC%9E%A5_%EA%BF%80%EB%AC%B4%ED%99%94%EA%B3%BC.jpg?type=w860",
		"https://shop-phinf.pstatic.net/20210925_89/1632543043460k67sA_GIF/%ED%95%B4%EB%82%A8_%ED%96%87%EB%AC%B4%ED%99%94%EA%B3%BC_%EC%B2%AD%EB%AC%B4%ED%99%94%EA%B3%BC_%EB%95%85%EB%81%9D%EB%AC%B4%ED%99%94%EA%B3%BC_(1).gif?type=wg860",
		"https://shop-phinf.pstatic.net/20210925_44/1632538480012GSc15_JPEG/%EB%AC%B4%ED%99%94%EA%B3%BC_(1).jpg?type=w860",
		"https://shop-phinf.pstatic.net/20210925_295/1632543076520FTC6E_GIF/%EB%AC%B4%ED%99%94%EA%B3%BC%EC%B2%AD_%ED%95%B4%EB%82%A8_%EB%AC%B4%ED%99%94%EA%B3%BC.gif?type=wg860",
		"https://shop-phinf.pstatic.net/20210925_79/1632543477806Eqkve_JPEG/%EB%AC%B4%ED%99%94%EA%B3%BC%EC%83%90%EB%9F%AC%EB%93%9C_%EC%B2%AD%EB%AC%B4%ED%99%94%EA%B3%BC.jpg?type=w860",
		"https://shop-phinf.pstatic.net/20200818_292/1597700829276rP5xc_JPEG/SE-890f057f-1796-47d6-96e8-51b619a92663.jpg?type=w860",
		"https://shop-phinf.pstatic.net/20200818_193/1597700855656FXMVC_JPEG/SE-ed362e3e-8e4f-42fe-a83f-922cad2545b6.jpg?type=w860",
		"https://shop-phinf.pstatic.net/20210925_217/1632543540215pSMa2_JPEG/%EB%AC%B4%ED%99%94%EA%B3%BC%EC%BF%A0%ED%82%A4_(1).jpg?type=w860"
	],
	"originalUrl": "https://cr.shopping.naver.com/adcr.nhn?x=KgdAboXE6RCi1w6O0reReP%2F%2F%2Fw%3D%3DsDW6VFIDyy0plNwIcIGDfaOdXgtjAZ%2F7BaReP%2Fk1mck2nm89iEA48wespqzxz5rWr1mwBwky31NbLXPXPPqBIo5F523jp1ZgrDZelMnmlOVAEL78pR0Tvi1Np9hsh%2BUweJxfYBSrxU%2BHc8r%2BjyXxpORDfSDBvRkBad9fdnOvVrJHxFVMtjMtyeSgq9z03u7SXI1c78hGogSi5qno9GG6%2FpquKWQN4b7WstTXVRp4V%2Fd2Kx7G3krbJiQXzryuwwOqJ8HOcT4r65HzE9YkLcuXqfbN1gSHZ%2BKBcKzTivBbdKI71TXOKt%2FKMeUqCtD3t9zqdd6tFREolldYWb1WWhps7i0TgrJHaF9Nmzv0GUBXkDjFTfkTEYHFdU5tuArjrjxkHl1oHpA%2BarJ2Mm1Apc2mNmbiAARlCMw%2B%2B0HEwK%2B9cIp5Af62d1rpzJrtufI%2FRMBupRNkuP7H0NWhAy%2BFIVKi3AgvIue18iyQEixffj02X3uRBD4xNe5J8EHVTQqw8%2FFPUBYK5Qcgbvo0lk8EClX9GeDass%2Bbr%2F7fNO3Z6P9F1imELXgT%2FrZUQmJ%2F0H%2BUywBV2Pf1KuEqZuY70%2Fh%2BM4QUfr4KoDr6us%2BRKRCOTdsWr9TI%3D&nvMid=83427876237&catId=50002193"
}