{
	"name": "크린랩 이나우스 친환경 접시 지름 200mm 10개입",
	"vendor": "타키온몰",
	"picUrl": "https://shopping-phinf.pstatic.net/main_8205613/82056137928.jpg",
	"thumbnailUrl": "https://shop-phinf.pstatic.net/20190517_273/tachyon233_1558052282686TieUl_JPEG/81358583311706762_1686035979.jpg?type=f100",
	"price": "840",
	"deliveryFee": "3000",
	"detailpicUrl": [
		"https://gi.esmplus.com/tachyon001/%EB%B0%B0%EC%86%A1%EC%9D%B4%EB%AF%B8%EC%A7%80/tachyon_head1.gif",
		"https://gi.esmplus.com/tachyon001/%EB%B0%B0%EC%86%A1%EC%9D%B4%EB%AF%B8%EC%A7%80/tachyon_head2.gif",
		"https://gi.esmplus.com/tachyon001/%EB%B0%B0%EC%86%A1%EC%9D%B4%EB%AF%B8%EC%A7%80/tachyon_head3.gif",
		"https://gi.esmplus.com/tachyon001/%ED%81%AC%EB%A6%B0%EC%A0%91%EC%8B%9C/7404/7404_d0.jpg",
		"https://gi.esmplus.com/tachyon001/%ED%81%AC%EB%A6%B0%EC%A0%91%EC%8B%9C/7404/7404_d1.jpg",
		"https://gi.esmplus.com/tachyon001/%ED%81%AC%EB%A6%B0%EC%A0%91%EC%8B%9C/7602/7602_d2.jpg",
		"https://gi.esmplus.com/tachyon001/%ED%81%AC%EB%A6%B0%EC%A0%91%EC%8B%9C/7602/7602_d3.jpg",
		"https://gi.esmplus.com/tachyon001/%ED%81%AC%EB%A6%B0%EC%A0%91%EC%8B%9C/7602/7602_d4.jpg",
		"https://gi.esmplus.com/tachyon001/%EB%B0%B0%EC%86%A1%EC%9D%B4%EB%AF%B8%EC%A7%80/%ED%83%80%ED%82%A4%EC%98%A8%EC%A0%84%ED%99%94%EB%B2%88%ED%98%B8.gif",
		"https://gi.esmplus.com/tachyon001/%EB%B0%B0%EC%86%A1%EC%9D%B4%EB%AF%B8%EC%A7%80/%EB%B0%B0%EC%86%A1%EA%B4%80%EB%A0%A8%EC%95%88%EB%82%B4.gif",
		"https://gi.esmplus.com/tachyon001/%EB%B0%B0%EC%86%A1%EC%9D%B4%EB%AF%B8%EC%A7%80/%EB%B0%B0%EC%86%A11.gif",
		"https://gi.esmplus.com/tachyon001/%EB%B0%B0%EC%86%A1%EC%9D%B4%EB%AF%B8%EC%A7%80/%EA%B5%90%ED%99%98%EB%B0%8F%EB%B0%98%ED%92%88%EC%95%88%EB%82%B4.gif",
		"https://gi.esmplus.com/tachyon001/%EB%B0%B0%EC%86%A1%EC%9D%B4%EB%AF%B8%EC%A7%80/%EB%B0%98%ED%92%88%EA%B4%80%EB%A0%A8.gif"
	],
	"originalUrl": "https://cr.shopping.naver.com/adcr.nhn?x=0pHOdbOnyhUn4LLA449H3f%2F%2F%2Fw%3D%3DsE5C4k3ZRBhUIF%2BY%2BD1HOJmzf4oqdmYNcDMHndxLo6pOzpU5SInebs0uf9Jek1Ew56Y7oeiZLJpASgaqcOe%2FZS83uC%2FlD7aHzPO5ryvoh7iMtzsEH5UDJAAkU5SucBtA6JxfYBSrxU%2BHc8r%2BjyXxpORDfSDBvRkBad9fdnOvVrJGP4JfbY4D5RL5XuaOGLmAqa96G4bqzaD7Bm%2Fb2PfxsQ6uKWQN4b7WstTXVRp4V%2Fd2Kx7G3krbJiQXzryuwwOqJOijB3OmobjStTFiHgzqGl5UHW7v%2FYSsco4xVj%2BPErZHzSIp2LZqyWfMNOJbeN6Bbpz1vh5LYs2x5261DI50vnU8JHvAJAtlSWKSbSwauPZKQcvhXOIUc%2BOtscHc0z%2B%2BijVuU41N0xYZFPhXPMpaNcwHIgF3xrgbnsZccYlVeQh8YQnIkV4o3Me65bcq2xCyP5TzEgu1LjGgJ2VFubwSW5ATJ97dEJHc04chQwLFGkyyLYK5Gh%2BD%2FEmc%2BsaN%2BIWd9pwWifSoTMKvwTNbUxIxams69C1ExeQLSjmPXTwsePs5oaKZHilHbuauHUigNM5KA&nvMid=82056137928&catId=50004834"
}